yamlator/__init__.py
yamlator/__main__.py
yamlator/exceptions.py
yamlator/types.py
yamlator/utils.py
yamlator/violations.py
yamlator/cmd/__init__.py
yamlator/cmd/core.py
yamlator/cmd/outputs/__init__.py
yamlator/cmd/outputs/base.py
yamlator/cmd/outputs/json_output.py
yamlator/cmd/outputs/table_output.py
yamlator/cmd/outputs/yaml_output.py
yamlator/grammar/grammar.lark
yamlator/parser/__init__.py
yamlator/parser/core.py
yamlator/parser/dependency.py
yamlator/parser/loaders.py
yamlator/validators/__init__.py
yamlator/validators/any_type_validator.py
yamlator/validators/base_validator.py
yamlator/validators/builtin_type_validator.py
yamlator/validators/core.py
yamlator/validators/entry_point_validator.py
yamlator/validators/enum_type_validator.py
yamlator/validators/list_validator.py
yamlator/validators/map_validator.py
yamlator/validators/optional_validator.py
yamlator/validators/regex_validator.py
yamlator/validators/required_validator.py
yamlator/validators/ruleset_validator.py
yamlator/validators/union_validator.py
yamlator-0.4.1.dist-info/LICENSE
yamlator-0.4.1.dist-info/METADATA
yamlator-0.4.1.dist-info/WHEEL
yamlator-0.4.1.dist-info/entry_points.txt
yamlator-0.4.1.dist-info/top_level.txt
yamlator-0.4.1.dist-info/RECORD
