Metadata-Version: 2.1
Name: yamlator
Version: 0.4.1
Summary: Yamlator is a CLI tool that allows a YAML file to be validated using a lightweight schema language
Home-page: https://github.com/ryan95f/yamlator
Author: Ryan Flynn
License: MIT
Platform: UNKNOWN
Classifier: Intended Audience :: Developers
Classifier: License :: OSI Approved :: MIT License
Classifier: Programming Language :: Python
Classifier: Programming Language :: Python :: 3
Classifier: Programming Language :: Python :: 3.6
Classifier: Programming Language :: Python :: 3.7
Classifier: Programming Language :: Python :: 3.8
Classifier: Programming Language :: Python :: 3.9
Classifier: Programming Language :: Python :: 3.10
Classifier: Operating System :: OS Independent
Requires-Python: >=3.6
License-File: LICENSE
Requires-Dist: lark (>=1.0.0)
Requires-Dist: PyYAML (>=5.4.1)
